<?xml version="1.0" encoding="utf-8"?>
<!DOCTYPE hibernate-mapping PUBLIC "-//Hibernate/Hibernate Mapping DTD 3.0//EN"
"http://www.hibernate.org/dtd/hibernate-mapping-3.0.dtd">
<!-- 
    Mapping file autogenerated by MyEclipse Persistence Tools
-->
<hibernate-mapping>
    <class name="com.his.mnis.entities.VwBqbrZy" table="VW_BQBR_ZY" schema="ZLHIS">
        <id name="rowkey" type="java.lang.String">
            <column name="ROWKEY" length="81" />
            <generator class="native" />
        </id>
        <property name="key1" type="java.lang.Long">
            <column name="KEY1" precision="18" scale="0" not-null="true" />
        </property>
        <property name="key2" type="java.lang.Integer">
            <column name="KEY2" precision="5" scale="0" not-null="true" />
        </property>
        <property name="bq" type="java.lang.String">
            <column name="BQ" length="40" />
        </property>
        <property name="chw" type="java.lang.String">
            <column name="CHW" length="10" />
        </property>
        <property name="bah" type="java.lang.String">
            <column name="BAH" length="40" />
        </property>
        <property name="xm" type="java.lang.String">
            <column name="XM" length="64" />
        </property>
        <property name="xb" type="java.lang.String">
            <column name="XB" length="4" />
        </property>
        <property name="nl" type="java.lang.String">
            <column name="NL" length="10" />
        </property>
        <property name="ksid" type="java.lang.String">
            <column name="KSID" length="40" />
        </property>
        <property name="ksmc" type="java.lang.String">
            <column name="KSMC" length="20" />
        </property>
        <property name="ysxm" type="java.lang.String">
            <column name="YSXM" length="20" />
        </property>
        <property name="hsxm" type="java.lang.String">
            <column name="HSXM" length="20" />
        </property>
        <property name="hldj" type="java.lang.String">
            <column name="HLDJ" length="80" />
        </property>
        <property name="fylb" type="java.lang.String">
            <column name="FYLB" length="10" />
        </property>
        <property name="ryrq" type="java.lang.String">
            <column name="RYRQ" length="10" />
        </property>
        <property name="jcflag" type="java.lang.String">
            <column name="JCFLAG" length="1" />
        </property>
        <property name="fylbBoxcolor" type="java.lang.String">
            <column name="FYLB_BOXCOLOR" length="12" />
        </property>
        <property name="dqbkzt" type="java.lang.String">
            <column name="DQBKZT" length="20" />
        </property>
        <property name="ryzd" type="java.lang.String">
            <column name="RYZD" length="4000" />
        </property>
        <property name="gmls" type="java.lang.String">
            <column name="GMLS" length="4000" />
        </property>
        <property name="shanshi" type="java.lang.String">
            <column name="SHANSHI" length="0" />
        </property>
        <property name="ssms" type="java.lang.String">
            <column name="SSMS" length="0" />
        </property>
        <property name="yems" type="java.lang.String">
            <column name="YEMS" length="0" />
        </property>
        <property name="zytsms" type="java.lang.String">
            <column name="ZYTSMS" length="44" />
        </property>
        <property name="aqtx" type="java.lang.String">
            <column name="AQTX" length="200" />
        </property>
    </class>
</hibernate-mapping>
